d2b_asl.py
d2b_asl-2.0.1.dist-info/METADATA
d2b_asl-2.0.1.dist-info/WHEEL
d2b_asl-2.0.1.dist-info/entry_points.txt
d2b_asl-2.0.1.dist-info/RECORD
