Metadata-Version: 2.1
Name: d2b-asl
Version: 2.0.1
Summary: Plugin for the d2b package to handle ASL data
Home-page: https://github.com/d2b-dev/d2b-asl
Keywords: neuroscience,neuroimaging,bids,d2b,plugin
Author: Andrew Ross
Author-email: andrew.ross.mail@gmail.com
Requires-Python: >=3.8,<4.0
Classifier: Intended Audience :: Developers
Classifier: Intended Audience :: Healthcare Industry
Classifier: Intended Audience :: Science/Research
Classifier: Operating System :: MacOS
Classifier: Operating System :: Microsoft :: Windows
Classifier: Operating System :: Unix
Classifier: Programming Language :: Python
Classifier: Programming Language :: Python :: 3
Classifier: Programming Language :: Python :: 3.8
Classifier: Programming Language :: Python :: 3.9
Classifier: Programming Language :: Python :: 3.10
Classifier: Programming Language :: Python :: 3.11
Classifier: Programming Language :: Python :: 3.12
Classifier: Topic :: Scientific/Engineering
Classifier: Topic :: Scientific/Engineering :: Bio-Informatics
Classifier: Topic :: Scientific/Engineering :: Medical Science Apps.
Classifier: Topic :: Software Development :: Libraries :: Python Modules
Classifier: Topic :: Utilities
Classifier: Typing :: Typed
Requires-Dist: d2b (>=1.1.4,<2.0.0)
Requires-Dist: nibabel (>=3.2.1,<4.0.0)
Project-URL: Documentation, https://github.com/d2b-dev/d2b-asl
Project-URL: Repository, https://github.com/d2b-dev/d2b-asl
